paged_list/__init__.py
paged_list/__main__.py
paged_list/main.py
paged_list/paged_list.py
paged_list-0.1.3.dist-info/METADATA
paged_list-0.1.3.dist-info/WHEEL
paged_list-0.1.3.dist-info/entry_points.txt
paged_list-0.1.3.dist-info/licenses/LICENSE
paged_list-0.1.3.dist-info/RECORD
