Metadata-Version: 2.4
Name: paged-list
Version: 0.1.3
Summary: A disk-backed list implementation for handling large datasets efficiently
Project-URL: Homepage, https://github.com/christensendaniel/paged-list
Project-URL: Documentation, https://paged-list.readthedocs.io/
Project-URL: Repository, https://github.com/christensendaniel/paged-list.git
Project-URL: Bug Tracker, https://github.com/christensendaniel/paged-list/issues
Project-URL: PyPI, https://pypi.org/project/paged-list/
Author-email: Christensen Daniel <christensen.daniel+pagedlist@outlook.com>
License: MIT
License-File: LICENSE
Keywords: chunking,data-processing,disk-backed,large-data,memory-efficient,serialization
Classifier: Development Status :: 4 - Beta
Classifier: Intended Audience :: Developers
Classifier: Intended Audience :: Science/Research
Classifier: License :: OSI Approved :: MIT License
Classifier: Operating System :: OS Independent
Classifier: Programming Language :: Python :: 3
Classifier: Programming Language :: Python :: 3.9
Classifier: Programming Language :: Python :: 3.10
Classifier: Programming Language :: Python :: 3.11
Classifier: Programming Language :: Python :: 3.12
Classifier: Programming Language :: Python :: 3.13
Classifier: Topic :: Database
Classifier: Topic :: Scientific/Engineering :: Information Analysis
Classifier: Topic :: Software Development :: Libraries :: Python Modules
Classifier: Topic :: System :: Archiving
Requires-Python: >=3.9
Provides-Extra: dev
Requires-Dist: black>=23.0; extra == 'dev'
Requires-Dist: flake8>=6.0; extra == 'dev'
Requires-Dist: hatch>=1.7.0; extra == 'dev'
Requires-Dist: isort>=5.0; extra == 'dev'
Requires-Dist: mypy>=1.0; extra == 'dev'
Requires-Dist: pre-commit>=3.0; extra == 'dev'
Requires-Dist: pytest-cov>=4.0; extra == 'dev'
Requires-Dist: pytest>=7.0; extra == 'dev'
Provides-Extra: docs
Requires-Dist: sphinx-rtd-theme>=1.0; extra == 'docs'
Requires-Dist: sphinx>=5.0; extra == 'docs'
Provides-Extra: examples
